Workbook

Sheet How to use
A1: SmartStudent — Pune Market Model
B4: WHAT THIS IS
B5: A live sizing model for the SmartStudent platform, scoped to Pune city only. Every figure on the Funnel, Revenue and Unit Economics sheets is a formula driven by the Assumptions sheet.
B7: HOW TO USE IT
B8: 1. Open the 'Assumptions' sheet. Every YELLOW cell is an input you can change.
B9: 2. Change one, and every number on the other sheets updates immediately.
B10: 3. Nothing else should be edited — grey and green cells are calculated.
B12: IMPORTANT — READ BEFORE USING THESE NUMBERS ANYWHERE
B13: These are MODELLED ESTIMATES, not researched facts. I have shown the full derivation so you can see exactly which assumption drives which output, and the 'Sources' sheet names the specific place to get each real number.
B14: Do not put these figures into an investor deck or a bank proposal until the inputs flagged with a confidence of LOW have been replaced with real data.
B16: THE ONE THING WORTH DOING FIRST
B17: UDISE+ (udiseplus.gov.in) publishes school-level enrolment for Pune district, filterable by board and grade, for free. About a day of work there replaces the entire top half of this model with hard data. Do that before spending any money on the build.
B19: SHEETS
... B25: Sources — where to get each real number

Sheet Assumptions
A1: Assumptions — edit the yellow cells only
A3: # | B3: Assumption | C3: Value | D3: Confidence | E3: Basis / what to check
A4: POPULATION & COHORT
A5: 1 | B5: Pune urban agglomeration population, 2026 | C5: 7400000 | D5: LOW | E5: Census 2011 UA ~5.05M extrapolated at ~2.7%/yr. Verify vs PMRDA projections.
A6: 2 | B6: Share of population aged 12-17 | C6: 0.095 | D6: LOW | E6: Urban metros run below the national ~11% (lower fertility). Verify vs Census age tables.
A7: 3 | B7: School enrolment rate, urban, this age band | C7: 0.96 | D7: MEDIUM | E7: Urban Maharashtra secondary enrolment. Verify vs UDISE+.
A9: BOARD SPLIT (must sum to 100%)
A10: 4 | B10: Maharashtra SSC / HSC | C10: 0.6 | D10: LOW | E10: UDISE+ gives the exact Pune district split. REPLACE THIS.
A11: 5 | B11: CBSE | C11: 0.24 | D11: LOW | E11: CBSE affiliated-school directory, filter by district.
A12: 6 | B12: ICSE / ISC | C12: 0.09 | D12: LOW | E12: CISCE school locator.
A13: 7 | B13: IGCSE / IB | C13: 0.02 | D13: LOW | E13: Small; count schools directly, there are few.
A14: 8 | B14: Other | C14: 0.05 | D14: LOW
A16: ADDRESSABILITY FILTERS
A17: 9 | B17: Has smartphone + home data access | C17: 0.88 | D17: MEDIUM | E17: Urban Pune penetration is high. TRAI / IAMAI reports.
A18: 10 | B18: Household already pays for supplementary learning | C18: 0.55 | D18: LOW | E18: NSSO Household Social Consumption: Education survey.
A19: 11 | B19: Of those, will pay for a DIGITAL product | C19: 0.35 | D19: LOW | E19: THE MOST IMPORTANT AND LEAST CERTAIN INPUT. Test with a landing page + Rs 15k of ads.
A21: THE WEDGE (SSC, Grades 9-10)
A22: 12 | B22: Share of SSC students in Grades 9-10 | C22: 0.36 | D22: MEDIUM | E22: 2 of 6 grades = 33%, weighted up slightly for board-year focus.
A23: 13 | B23: Reachable via coaching classes / schools | C23: 0.6 | D23: LOW | E23: Count Pune coaching institutes via GST directory + Google Maps.
A24: 14 | B24: Share of that reachable pool won by month 24 | C24: 0.05 | D24: LOW | E24: Judgement. 4-7% is the plausible band.
A26: PRICING
A27: 15 | B27: Institute seat price, per student per month (Rs) | C27: 90 | D27: MEDIUM | E27: Validate with 15 coaching class visits.
A28: 16 | B28: Institute platform fee, per month (Rs) | C28: 6000 | D28: MEDIUM | E28: Test engine + batches + analytics + branding.
A29: 17 | B29: B2C direct price, per year (Rs) | C29: 1999 | D29: MEDIUM | E29: Anchored below Physics Wallah's reference price.
A31: TRACTION — MONTH 12
A32: 18 | B32: Institutes signed | C32: 12 | D32: LOW | E32: Judgement, assumes founder-led sales.
A33: 19 | B33: Avg paying students per institute | C33: 110 | D33: MEDIUM | E33: Typical mid-size Pune tutorial batch load.
A34: 20 | B34: B2C direct paying students | C34: 400 | D34: LOW | E34: Organic + referral only; no paid ads in year 1.
A36: TRACTION — MONTH 24
A37: 21 | B37: Institutes signed | C37: 40 | D37: LOW | E37: Judgement.
A38: 22 | B38: Avg paying students per institute | C38: 130 | D38: MEDIUM
A39: 23 | B39: B2C direct paying students | C39: 1800 | D39: LOW
A41: COST SIDE
A42: 24 | B42: AI + infra cost per student per month (Rs) | C42: 28 | D42: MEDIUM | E42: Assumes the AI Gateway response cache is built. Without it, budget Rs 60-120.
A43: 25 | B43: CAC per student — institute channel (Rs) | C43: 180 | D43: LOW | E43: One sale brings 100+ students.
A44: 26 | B44: CAC per student — B2C direct (Rs) | C44: 1000 | D44: LOW | E44: Parent-facing acquisition is expensive.
A45: 27 | B45: Annual retention — institute channel | C45: 0.7 | D45: LOW | E45: Institutes renew in bulk.
A46: 28 | B46: Annual retention — B2C direct | C46: 0.35 | D46: LOW | E46: Weak point of the B2C model.
B48: Board split check (must equal 100%) | C48: =Assumptions!$C$10+Assumptions!$C$11+Assumptions!$C$12+Assumptions!$C$13+Assumptions!$C$14

Sheet Market Funnel
A1: Market funnel — Pune city, Grades 7-12
A3: Step | B3: Value | C3: Formula in words | D3: Note
A4: Pune urban agglomeration population, 2026 | B4: =Assumptions!$C$5 | C4: input
A5: x share aged 12-17 | B5: =Assumptions!$C$6 | C5: input
A6: → children in the Grade 7-12 age band | B6: =$B$4*$B$5 | C6: population x age share
A7: x school enrolment rate | B7: =Assumptions!$C$7 | C7: input
A8: → TAM: students in school, Grades 7-12 | B8: =$B$6*$B$7 | C8: age band x enrolment | D8: Total addressable market, Pune
A10: SSC / HSC students | B10: =$B$8*Assumptions!$C$10 | C10: TAM x SSC share | D10: The beachhead
A11: CBSE students | B11: =$B$8*Assumptions!$C$11 | C11: TAM x CBSE share | D11: Phase 3 expansion
A12: ICSE / ISC students | B12: =$B$8*Assumptions!$C$12 | C12: TAM x ICSE share | D12: Later
A13: IGCSE / IB students | B13: =$B$8*Assumptions!$C$13 | C13: TAM x IGCSE share | D13: Last — licensing risk
A15: x has smartphone + data | B15: =Assumptions!$C$17 | C15: input
A16: → digitally reachable students | B16: =$B$8*$B$15 | C16: TAM x reachability
A17: x household pays for supplementary learning | B17: =Assumptions!$C$18 | C17: input
A18: → students in paying households | B18: =$B$16*$B$17 | C18: reachable x paying households
A19: x will pay for a DIGITAL product | B19: =Assumptions!$C$19 | C19: input | D19: Least certain input in the model
A20: → SAM: serviceable addressable market | B20: =$B$18*$B$19 | C20: paying households x digital willingness | D20: Pune, all boards, Grades 7-12
A22: SSC students in Grades 9-10 | B22: =$B$10*Assumptions!$C$22 | C22: SSC students x grade 9-10 share | D22: The wedge cohort
A23: x reachable via institutes | B23: =Assumptions!$C$23 | C23: input
A24: → institute-reachable wedge pool | B24: =$B$22*$B$23 | C24: wedge x institute reach
A25: x share won by month 24 | B25: =Assumptions!$C$24 | C25: input
A26: → SOM: winnable paying students, month 24 | B26: =$B$24*$B$25 | C26: pool x capture rate | D26: Cross-check against the Revenue Model sheet

Sheet Revenue Model
A1: Revenue projection — Pune only
A3: Line | B3: Month 12 | C3: Month 24 | D3: Note
A4: Institutes signed | B4: =Assumptions!$C$32 | C4: =Assumptions!$C$37
A5: Avg paying students per institute | B5: =Assumptions!$C$33 | C5: =Assumptions!$C$38
A6: Students via institutes | B6: =B4*B5 | C6: =C4*C5
A7: B2C direct paying students | B7: =Assumptions!$C$34 | C7: =Assumptions!$C$39 | D7: Organic + referral only
A8: TOTAL PAYING STUDENTS | B8: =B6+B7 | C8: =C6+C7
A10: Institute seat revenue (Rs/yr) | B10: =B6*Assumptions!$C$27*12 | C10: =C6*Assumptions!$C$27*12 | D10: seats x price x 12
A11: Institute platform fees (Rs/yr) | B11: =B4*Assumptions!$C$28*12 | C11: =C4*Assumptions!$C$28*12 | D11: institutes x fee x 12
A12: B2C direct revenue (Rs/yr) | B12: =B7*Assumptions!$C$29 | C12: =C7*Assumptions!$C$29
A13: TOTAL ARR (Rs) | B13: =B10+B11+B12 | C13: =C10+C11+C12
A14: TOTAL ARR (Rs lakh) | B14: =B13/100000 | C14: =C13/100000
A16: AI + infra cost (Rs/yr) | B16: =B8*Assumptions!$C$42*12 | C16: =C8*Assumptions!$C$42*12 | D16: Assumes the response cache is built
A17: Gross profit before content & salaries (Rs) | B17: =B13-B16 | C17: =C13-C16
A18: Gross margin | B18: =B17/B13 | C18: =C17/C13 | D18: Before content, salaries and sales cost

Sheet Unit Economics
A1: Unit economics — B2B2C vs B2C direct
A3: Metric | B3: B2B2C (institute) | C3: B2C direct | D3: Note
A4: Revenue per student per year (Rs) | B4: =Assumptions!$C$27*12 | C4: =Assumptions!$C$29 | D4: Institute figure excludes the platform fee
A5: AI + infra cost per student per year (Rs) | B5: =Assumptions!$C$42*12 | C5: =Assumptions!$C$42*12
A6: Gross profit per student per year (Rs) | B6: =B4-B5 | C6: =C4-C5
A7: Gross margin | B7: =B6/B4 | C7: =C6/C4
A9: CAC per student (Rs) | B9: =Assumptions!$C$43 | C9: =Assumptions!$C$44 | D9: Marketing/sales spend only — excludes founder and salaried sales time, which flatters the institute column
A10: Payback period (months) | B10: =B9/(B6/12) | C10: =C9/(C6/12) | D10: CAC / monthly gross profit
A12: Annual retention | B12: =Assumptions!$C$45 | C12: =Assumptions!$C$46
A13: Avg customer lifetime (years) | B13: =1/(1-B12) | C13: =1/(1-C12)
A14: LTV (Rs) | B14: =B6*B13 | C14: =C6*C13 | D14: Gross profit x lifetime
A15: LTV : CAC ratio | B15: =B14/B9 | C15: =C14/C9 | D15: Above 3.0 is healthy
A17: Read the Payback and LTV:CAC rows together — they are the whole argument for selling to institutes before selling to parents.
A18: The institute LTV:CAC looks very high because CAC here counts marketing spend only. Add a salesperson's salary and it lands nearer 4-6 — still comfortably ahead of the B2C column, which is the point.

Sheet Pune Ceiling
A1: What Pune alone maxes out at
A3: Scenario | B3: Share of Pune SAM | C3: Paying students | D3: ARR (Rs crore)
A4: Blended revenue per student per year (Rs) | B4: =Assumptions!$C$27*12*0.75+Assumptions!$C$29*0.25 | C4: 75% institute-priced, 25% B2C-priced
A6: Base — modest outcome | B6: 0.05 | C6: ='Market Funnel'!$B$20*B6 | D6: =C6*$B$4/10000000
A7: Good outcome | B7: 0.1 | C7: ='Market Funnel'!$B$20*B7 | D7: =C7*$B$4/10000000
A8: Strong outcome | B8: 0.18 | C8: ='Market Funnel'!$B$20*B8 | D8: =C8*$B$4/10000000
A9: Dominant — near-ceiling | B9: 0.25 | C9: ='Market Funnel'!$B$20*B9 | D9: =C9*$B$4/10000000
A12: THE POINT OF THIS SHEET
A13: Even a dominant position in Pune caps the business at a few crore of ARR.
A14: Pune is the right beachhead and the wrong final market.
A16: Maharashtra SSC and HSC each draw roughly 14-16 lakh candidates per year statewide,
A17: against roughly 1.4 lakh SSC students in Grades 9-10 in all of Pune.
A18: Statewide is on the order of 20x the Pune opportunity — on identical content.
A20: That is the strongest argument for the SSC-first strategy: the content built for Pune
A21: is the same content that unlocks a market twenty times larger, with no rebuild.

Sheet Sources
A1: Where to get the real numbers
A3: Input to replace | B3: Source | C3: How | D3: Cost
A4: Students per grade, per board, Pune | B4: UDISE+ (udiseplus.gov.in) | C4: School-level enrolment, filterable to Pune district by board and grade. The single best source. Start here. | D4: Free
A5: Pune urban population, current | B5: Census 2011 + PMRDA / PMC projections | C5: Use the 2011 UA figure as the base and the corporation's own growth projection. | D5: Free
A6: SSC / HSC candidate counts | B6: MSBSHSE (mahahsscboard.in) | C6: Annual result press releases give exact appeared-candidate counts, district-wise. | D6: Free
A7: CBSE school count in Pune | B7: CBSE affiliated-school directory | C7: Filter the official list by district; multiply by average enrolment. | D7: Free
A8: ICSE / ISC school count | B8: CISCE school locator | C8: Same approach as CBSE. | D8: Free
A9: Coaching class count in Pune | B9: GST directory + Google Maps | C9: Maharashtra shops-and-establishment registrations; cross-check with a Maps count per locality. Rough, but enough to size the channel. | D9: Free / low
A10: Household spend on tuition | B10: NSSO Household Social Consumption: Education | C10: Gives urban Maharashtra spend per student on private coaching. | D10: Free
A11: Willingness to pay for digital | B11: Your own landing-page test | C11: A landing page plus about Rs 15,000 of targeted ads gives you the real conversion rate in a week. Cheaper and more honest than any survey. | D11: ~Rs 15k
A12: Institute price acceptance | B12: 15 coaching class visits | C12: Ask one question: would you pay Rs 90 per student per month for a test engine with weakness reports? Three yeses justifies the build. | D12: Free
